llama_index/packs/redis_ingestion_pipeline/__init__.py
llama_index/packs/redis_ingestion_pipeline/base.py
llama_index_packs_redis_ingestion_pipeline-0.3.0.dist-info/METADATA
llama_index_packs_redis_ingestion_pipeline-0.3.0.dist-info/WHEEL
llama_index_packs_redis_ingestion_pipeline-0.3.0.dist-info/RECORD
