Metadata-Version: 2.1
Name: llama-index-packs-redis-ingestion-pipeline
Version: 0.3.0
Summary: llama-index packs redis_ingestion_pipeline integration
License: MIT
Keywords: index,ingestion,pipeline,redis
Author: Your Name
Author-email: you@example.com
Maintainer: logan-markewich
Requires-Python: >=3.9,<4.0
Classifier: License :: OSI Approved :: MIT License
Classifier: Programming Language :: Python :: 3
Classifier: Programming Language :: Python :: 3.9
Classifier: Programming Language :: Python :: 3.10
Classifier: Programming Language :: Python :: 3.11
Classifier: Programming Language :: Python :: 3.12
Requires-Dist: llama-index-core (>=0.12.0,<0.13.0)
Requires-Dist: llama-index-storage-kvstore-redis (>=0.3.0,<0.4.0)
Requires-Dist: llama-index-vector-stores-redis (>=0.4.0,<0.5.0)
